nicegui_blackjack/__init__.py
nicegui_blackjack/blackjack.py
nicegui_blackjack/py.typed
nicegui_blackjack-0.2.8.dist-info/METADATA
nicegui_blackjack-0.2.8.dist-info/WHEEL
nicegui_blackjack-0.2.8.dist-info/entry_points.txt
nicegui_blackjack-0.2.8.dist-info/licenses/LICENSE
nicegui_blackjack-0.2.8.dist-info/RECORD
